exile/__init__.py
exile/botocore_signers.py
exile/cli.py
exile/exceptions.py
exile/version.py
exile/scard/__init__.py
exile/scard/const.py
exile/util/__init__.py
exile/ykoath/__init__.py
exile/ykoath/const.py
exile-0.1.1.dist-info/LICENSE
exile-0.1.1.dist-info/METADATA
exile-0.1.1.dist-info/WHEEL
exile-0.1.1.dist-info/top_level.txt
exile-0.1.1.dist-info/RECORD
